RPALite/__init__.py
RPALite/easyocr_handler.py
RPALite/image_handler.py
RPALite/paddleocr_handler.py
RPALite/rpalite.py
rpalite-0.2.0.dist-info/licenses/LICENSE
rpalite-0.2.0.dist-info/WHEEL
rpalite-0.2.0.dist-info/METADATA
rpalite-0.2.0.dist-info/RECORD
