Metadata-Version: 2.4
Name: RPALite
Version: 0.2.0
Summary: Open Source RPA (Robotic Process Automation) Library for Python and Robot Framework
Author: RPALite contributors
Requires-Python: >=3.8
Classifier: Framework :: Robot Framework :: Library
Classifier: Operating System :: Microsoft :: Windows
Classifier: Development Status :: 2 - Pre-Alpha
Classifier: Programming Language :: Python :: 3
Classifier: License :: OSI Approved :: Apache Software License
License-File: LICENSE
Project-URL: Documentation, https://jieliu2000.github.io/RPALite/
Project-URL: Home, https://github.com/jieliu2000/RPALite
Project-URL: Issues, https://github.com/jieliu2000/RPALite/issues
